googlesheets_leo/__init__.py
googlesheets_leo/googlesheets.py
googlesheets_leo-0.1.1.dist-info/METADATA
googlesheets_leo-0.1.1.dist-info/WHEEL
googlesheets_leo-0.1.1.dist-info/RECORD
