Metadata-Version: 2.1
Name: googlesheets-leo
Version: 0.1.1
Summary: 
Author: leomoraesguitar
Author-email: 123950901+leomoraesguitar@users.noreply.github.com
Requires-Python: >=3.11,<4.0
Classifier: Programming Language :: Python :: 3
Classifier: Programming Language :: Python :: 3.11
Requires-Dist: google-api-python-client (>=2.104.0,<3.0.0)
Requires-Dist: google-auth-httplib2 (>=0.1.1,<0.2.0)
Requires-Dist: google-auth-oauthlib (>=1.1.0,<2.0.0)
